{
  "title": "Restaurant Menu Item",
  "difficulty": "medium",
  "target": {
    "html": "<div class=\"menu-card\">\n  <div class=\"menu-header\">\n    <span class=\"category-tag\">Chef's Special</span>\n    <span class=\"dietary-badge vegan\">V</span>\n  </div>\n  <div class=\"menu-body\">\n    <div class=\"item-info\">\n      <h2 class=\"item-name\">Truffle Risotto</h2>\n      <p class=\"item-desc\">Arborio rice slow-cooked with wild mushrooms, aged parmesan, and a generous drizzle of black truffle oil.</p>\n      <div class=\"item-meta\">\n        <span class=\"meta-pill\">🕐 25 min</span>\n        <span class=\"meta-pill\">🔥 480 kcal</span>\n        <span class=\"meta-pill\">⭐ 4.9</span>\n      </div>\n    </div>\n    <div class=\"item-side\">\n      <div class=\"item-image-placeholder\"></div>\n      <div class=\"price-row\">\n        <span class=\"price\">$24.00</span>\n        <button class=\"add-btn\">+ Add</button>\n      </div>\n    </div>\n  </div>\n  <div class=\"menu-footer\">\n    <span class=\"footer-label\">Pairs well with:</span>\n    <span class=\"pairing-chip\">Pinot Noir</span>\n    <span class=\"pairing-chip\">Sparkling Water</span>\n    <span class=\"pairing-chip\">Tiramisu</span>\n  </div>\n</div>",
    "css": ":root {\n  --card-bg: #ffffff;\n  --card-border: #e8e0d5;\n  --card-radius: 16px;\n  --header-bg: #2d1b0e;\n  --category-color: #f5c97a;\n  --vegan-bg: #4a7c59;\n  --vegan-text: #ffffff;\n  --item-name-color: #1a1008;\n  --desc-color: #6b5744;\n  --meta-pill-bg: #f4ede4;\n  --meta-pill-color: #7a5c44;\n  --image-bg: #e8ddd0;\n  --image-accent: #c4a882;\n  --price-color: #2d1b0e;\n  --btn-bg: #c0392b;\n  --btn-text: #ffffff;\n  --btn-radius: 8px;\n  --footer-bg: #faf6f1;\n  --footer-border: #e8e0d5;\n  --footer-label-color: #a0856c;\n  --chip-bg: #ede4d8;\n  --chip-color: #6b4f37;\n}\n\n.menu-card {\n  background: var(--card-bg);\n  border: 1.5px solid var(--card-border);\n  border-radius: var(--card-radius);\n  width: 500px;\n  overflow: hidden;\n}\n\n.menu-header {\n  background: var(--header-bg);\n  padding: 10px 16px;\n  display: flex;\n  align-items: center;\n  justify-content: space-between;\n}\n\n.category-tag {\n  color: var(--category-color);\n  font-size: 12px;\n  font-weight: 700;\n  letter-spacing: 1.2px;\n  text-transform: uppercase;\n}\n\n.dietary-badge {\n  font-size: 11px;\n  font-weight: 800;\n  width: 22px;\n  height: 22px;\n  border-radius: 50%;\n  display: flex;\n  align-items: center;\n  justify-content: center;\n}\n\n.dietary-badge.vegan {\n  background: var(--vegan-bg);\n  color: var(--vegan-text);\n}\n\n.menu-body {\n  padding: 16px;\n  display: flex;\n  gap: 16px;\n  align-items: flex-start;\n}\n\n.item-info {\n  flex: 1;\n}\n\n.item-name {\n  font-size: 20px;\n  font-weight: 800;\n  color: var(--item-name-color);\n  margin: 0 0 8px 0;\n  line-height: 1.2;\n}\n\n.item-desc {\n  font-size: 13px;\n  color: var(--desc-color);\n  line-height: 1.6;\n  margin: 0 0 12px 0;\n}\n\n.item-meta {\n  display: flex;\n  gap: 6px;\n  flex-wrap: wrap;\n}\n\n.meta-pill {\n  background: var(--meta-pill-bg);\n  color: var(--meta-pill-color);\n  font-size: 12px;\n  font-weight: 600;\n  padding: 4px 10px;\n  border-radius: 20px;\n}\n\n.item-side {\n  display: flex;\n  flex-direction: column;\n  align-items: center;\n  gap: 10px;\n  flex-shrink: 0;\n}\n\n.item-image-placeholder {\n  width: 110px;\n  height: 90px;\n  background: var(--image-bg);\n  border-radius: 12px;\n  border: 2px solid var(--image-accent);\n}\n\n.price-row {\n  display: flex;\n  align-items: center;\n  gap: 8px;\n  width: 100%;\n  justify-content: space-between;\n}\n\n.price {\n  font-size: 18px;\n  font-weight: 800;\n  color: var(--price-color);\n}\n\n.add-btn {\n  background: var(--btn-bg);\n  color: var(--btn-text);\n  border: none;\n  border-radius: var(--btn-radius);\n  padding: 6px 12px;\n  font-size: 13px;\n  font-weight: 700;\n  cursor: pointer;\n}\n\n.menu-footer {\n  background: var(--footer-bg);\n  border-top: 1.5px solid var(--footer-border);\n  padding: 10px 16px;\n  display: flex;\n  align-items: center;\n  gap: 8px;\n  flex-wrap: wrap;\n}\n\n.footer-label {\n  font-size: 12px;\n  font-weight: 600;\n  color: var(--footer-label-color);\n  margin-right: 2px;\n}\n\n.pairing-chip {\n  background: var(--chip-bg);\n  color: var(--chip-color);\n  font-size: 12px;\n  font-weight: 600;\n  padding: 4px 10px;\n  border-radius: 20px;\n}"
  },
  "starter": {
    "html": "<div class=\"menu-card\">\n  <div class=\"menu-header\">\n    <span class=\"category-tag\">Chef's Special</span>\n    <span class=\"dietary-badge vegan\">V</span>\n  </div>\n  <div class=\"menu-body\">\n    <div class=\"item-info\">\n      <h2 class=\"item-name\">Truffle Risotto</h2>\n      <p class=\"item-desc\">Arborio rice slow-cooked with wild mushrooms, aged parmesan, and a generous drizzle of black truffle oil.</p>\n      <div class=\"item-meta\">\n        <span class=\"meta-pill\">🕐 25 min</span>\n        <span class=\"meta-pill\">🔥 480 kcal</span>\n        <span class=\"meta-pill\">⭐ 4.9</span>\n      </div>\n    </div>\n    <div class=\"item-side\">\n      <div class=\"item-image-placeholder\"></div>\n      <div class=\"price-row\">\n        <span class=\"price\">$24.00</span>\n        <button class=\"add-btn\">+ Add</button>\n      </div>\n    </div>\n  </div>\n  <div class=\"menu-footer\">\n    <span class=\"footer-label\">Pairs well with:</span>\n    <span class=\"pairing-chip\">Pinot Noir</span>\n    <span class=\"pairing-chip\">Sparkling Water</span>\n    <span class=\"pairing-chip\">Tiramisu</span>\n  </div>\n</div>",
    "css": ":root {\n  --card-bg: #ffffff;\n  --card-border: #e8e0d5;\n  --card-radius: 16px;\n  --header-bg: #2d1b0e;\n  --category-color: #f5c97a;\n  --vegan-bg: #4a7c59;\n  --vegan-text: #ffffff;\n  --item-name-color: #1a1008;\n  --desc-color: #6b5744;\n  --meta-pill-bg: #f4ede4;\n  --meta-pill-color: #7a5c44;\n  --image-bg: #e8ddd0;\n  --image-accent: #c4a882;\n  --price-color: #2d1b0e;\n  --btn-bg: #c0392b;\n  --btn-text: #ffffff;\n  --btn-radius: 8px;\n  --footer-bg: #faf6f1;\n  --footer-border: #e8e0d5;\n  --footer-label-color: #a0856c;\n  --chip-bg: #ede4d8;\n  --chip-color: #6b4f37;\n}\n\n.menu-card {\n}\n\n.menu-header {\n}\n\n.category-tag {\n}\n\n.dietary-badge {\n}\n\n.dietary-badge.vegan {\n}\n\n.menu-body {\n}\n\n.item-info {\n}\n\n.item-name {\n}\n\n.item-desc {\n}\n\n.item-meta {\n}\n\n.meta-pill {\n}\n\n.item-side {\n}\n\n.item-image-placeholder {\n}\n\n.price-row {\n}\n\n.price {\n}\n\n.add-btn {\n}\n\n.menu-footer {\n}\n\n.footer-label {\n}\n\n.pairing-chip {\n}"
  },
  "date": "2026-03-18",
  "timeLimit": 600
}